topas2numpy/__init__.py
topas2numpy/binned.py
topas2numpy/ntuple.py
topas2numpy-0.2.0.dist-info/top_level.txt
topas2numpy-0.2.0.dist-info/METADATA
topas2numpy-0.2.0.dist-info/DESCRIPTION.rst
topas2numpy-0.2.0.dist-info/metadata.json
topas2numpy-0.2.0.dist-info/WHEEL
topas2numpy-0.2.0.dist-info/RECORD
